{
  "year1": {
    "type1": [
      { "title": "The part you play", "term": "1학기 중간", "speed": 512 },
      {
        "title": "Dolor est ut dolore id nisi aliqua aliquip esse cillum enim veniam.",
        "term": "1학기 중간",
        "speed": 123
      },
      {
        "title": "Ullamco Lorem cupidatat ea proident eu cupidatat enim.",
        "term": "1학기 기말",
        "speed": 242
      }
    ],
    "type2": [
      {
        "title": "Irure laboris labore non ullamco velit excepteur quis in esse.",
        "term": "2학기 중간",
        "speed": 22
      },
      {
        "title": "In mollit qui aliqua reprehenderit laboris ex ullamco id est sunt mollit sit.",
        "term": "1학기 중간",
        "speed": 23
      },
      {
        "title": "Officia cupidatat est duis nulla laboris magna aliqua nisi id qui.",
        "term": "1학기 중간",
        "speed": 41
      }
    ]
  },
  "year2": {
    "type1": [
      {
        "title": "Cupidatat non veniam tempor laboris elit non.",
        "term": "1학기 중간",
        "speed": 102
      },
      {
        "title": "Dolor reprehenderit in in enim.",
        "term": "2학기 중간",
        "speed": 243
      },
      {
        "title": "Labore tempor proident ex reprehenderit in proident adipisicing pariatur nisi veniam cillum.",
        "term": "1학기 중간",
        "speed": 392
      }
    ],
    "type2": [
      {
        "title": "Culpa esse adipisicing velit sint et.",
        "term": "2학기 중간",
        "speed": 221
      },
      {
        "title": "Eu sunt esse duis adipisicing laborum.",
        "term": "1학기 중간",
        "speed": 731
      },
      {
        "title": "Aliquip nisi cillum elit ut minim reprehenderit sint eiusmod ex duis consectetur cupidatat.",
        "term": "2학기 중간",
        "speed": 441
      }
    ]
  },
  "year3": {
    "type1": [
      {
        "title": "Eiusmod enim officia ipsum esse laboris dolore.",
        "term": "1학기 중간",
        "speed": 512
      },
      {
        "title": "Voluptate eiusmod officia nisi veniam dolore et ea ipsum non est et nulla officia.",
        "term": "1학기 중간",
        "speed": 123
      },
      {
        "title": "Enim adipisicing voluptate consectetur aliqua laboris.",
        "term": "1학기 기말",
        "speed": 242
      }
    ],
    "type2": [
      {
        "title": "Amet sunt labore in voluptate voluptate labore sint do aliquip veniam non sunt ut.",
        "term": "2학기 중간",
        "speed": 122
      },
      {
        "title": "Aliqua cillum ad exercitation non ullamco.",
        "term": "1학기 중간",
        "speed": 123
      },
      {
        "title": "Ad sint laboris cillum fugiat eu laborum ad esse sint est fugiat.",
        "term": "1학기 중간",
        "speed": 41
      }
    ]
  }
}
